fwOper/__init__.py
fwOper/acg.py
fwOper/acl.py
fwOper/common.py
fwOper/entity.py
fwOper/fwObj.py
fwOper/instances.py
fwOper/member.py
fwOper/route.py
fwOper/static.py
fwOper-0.0.4.dist-info/LICENSE
fwOper-0.0.4.dist-info/METADATA
fwOper-0.0.4.dist-info/WHEEL
fwOper-0.0.4.dist-info/top_level.txt
fwOper-0.0.4.dist-info/RECORD
