Metadata-Version: 2.1
Name: fwOper
Version: 0.0.4
Summary: Cisco Firewall Helper Package
Home-page: https://github.com/alias1978/fwOper
Author: ALIASGAR - ALI
Author-email: aholo2000@gmail.com
License: UNKNOWN
Platform: UNKNOWN
Classifier: Programming Language :: Python :: 3
Classifier: License :: OSI Approved :: MIT License
Classifier: Operating System :: OS Independent
Requires-Python: >=3.7
License-File: LICENSE
Requires-Dist: nettoolkit
